gym_soarm/__init__.py
gym_soarm/assets/assets/base_motor_holder_so101_v1.part
gym_soarm/assets/assets/base_motor_holder_so101_v1.stl
gym_soarm/assets/assets/base_so101_v2.part
gym_soarm/assets/assets/base_so101_v2.stl
gym_soarm/assets/assets/motor_holder_so101_base_v1.part
gym_soarm/assets/assets/motor_holder_so101_base_v1.stl
gym_soarm/assets/assets/motor_holder_so101_wrist_v1.part
gym_soarm/assets/assets/motor_holder_so101_wrist_v1.stl
gym_soarm/assets/assets/moving_jaw_so101_v1.part
gym_soarm/assets/assets/moving_jaw_so101_v1.stl
gym_soarm/assets/assets/rotation_pitch_so101_v1.part
gym_soarm/assets/assets/rotation_pitch_so101_v1.stl
gym_soarm/assets/assets/sts3215_03a_no_horn_v1.part
gym_soarm/assets/assets/sts3215_03a_no_horn_v1.stl
gym_soarm/assets/assets/sts3215_03a_v1.part
gym_soarm/assets/assets/sts3215_03a_v1.stl
gym_soarm/assets/assets/under_arm_so101_v1.part
gym_soarm/assets/assets/under_arm_so101_v1.stl
gym_soarm/assets/assets/upper_arm_so101_v1.part
gym_soarm/assets/assets/upper_arm_so101_v1.stl
gym_soarm/assets/assets/waveshare_mounting_plate_so101_v2.part
gym_soarm/assets/assets/waveshare_mounting_plate_so101_v2.stl
gym_soarm/assets/assets/wrist_roll_follower_so101_v1.part
gym_soarm/assets/assets/wrist_roll_follower_so101_v1.stl
gym_soarm/assets/assets/wrist_roll_pitch_so101_v2.part
gym_soarm/assets/assets/wrist_roll_pitch_so101_v2.stl
gym_soarm/assets/scene.xml
gym_soarm/assets/so-arm100.xml
gym_soarm/assets/tabletop.stl
gym_soarm/constants.py
gym_soarm/env.py
gym_soarm/tasks/__init__.py
gym_soarm/tasks/reward_wrapper.py
gym_soarm/tasks/sim.py
gym_soarm-0.4.0.dist-info/METADATA
gym_soarm-0.4.0.dist-info/WHEEL
gym_soarm-0.4.0.dist-info/RECORD
