Metadata-Version: 2.4
Name: gym-soarm
Version: 0.4.0
Summary: A gymnasium environment for SO-ARM100 single-arm manipulation based on gym-aloha
License: Apache-2.0
Keywords: robotics,deep,reinforcement,learning,so-arm,single-arm,environment,gym,gymnasium,dm-control,mujoco
Author: Masato Kawamura (masato-ka)
Author-email: jp6uzv@gmail.com
Requires-Python: >=3.10,<4.0
Classifier: Development Status :: 3 - Alpha
Classifier: Intended Audience :: Developers
Classifier: License :: OSI Approved :: Apache Software License
Classifier: Programming Language :: Python :: 3
Classifier: Programming Language :: Python :: 3.10
Classifier: Programming Language :: Python :: 3.11
Classifier: Programming Language :: Python :: 3.12
Classifier: Programming Language :: Python :: 3.13
Classifier: Programming Language :: Python :: 3.14
Classifier: Topic :: Software Development :: Build Tools
Provides-Extra: dev
Provides-Extra: test
Requires-Dist: debugpy (>=1.8.1) ; extra == "dev"
Requires-Dist: dm-control (>=1.0.14)
Requires-Dist: gymnasium (>=0.29.1)
Requires-Dist: imageio[ffmpeg] (>=2.34.0)
Requires-Dist: mujoco (>=2.3.7,<3.0.0)
Requires-Dist: pre-commit (>=3.7.0) ; extra == "dev"
Requires-Dist: pytest (>=8.1.0) ; extra == "test"
Requires-Dist: pytest-cov (>=5.0.0) ; extra == "test"
